[
  {
    "both":1.0091,
    "male":1.0765,
    "female":0.9451
  },
  {
    "both":0.057,
    "male":0.0609,
    "female":0.053
  },
  {
    "both":0.0085,
    "male":0.0099,
    "female":0.0071
  },
  {
    "both":0.0081,
    "male":0.0096,
    "female":0.0065
  },
  {
    "both":0.0212,
    "male":0.0286,
    "female":0.0135
  },
  {
    "both":0.0404,
    "male":0.056,
    "female":0.0238
  },
  {
    "both":0.0434,
    "male":0.059,
    "female":0.0271
  },
  {
    "both":0.0526,
    "male":0.067,
    "female":0.0377
  },
  {
    "both":0.0722,
    "male":0.0919,
    "female":0.052
  },
  {
    "both":0.1064,
    "male":0.1349,
    "female":0.077
  },
  {
    "both":0.1697,
    "male":0.2165,
    "female":0.1221
  },
  {
    "both":0.2695,
    "male":0.3527,
    "female":0.1858
  },
  {
    "both":0.4096,
    "male":0.558,
    "female":0.2628
  },
  {
    "both":0.655,
    "male":0.9258,
    "female":0.3944
  },
  {
    "both":0.9533,
    "male":1.3715,
    "female":0.5658
  },
  {
    "both":1.4734,
    "male":2.1248,
    "female":0.9059
  },
  {
    "both":2.5689,
    "male":3.6836,
    "female":1.6927
  },
  {
    "both":4.7211,
    "male":6.7592,
    "female":3.3816
  },
  {
    "both":8.3634,
    "male":11.6406,
    "female":6.7425
  },
  {
    "both":14.6242,
    "male":19.4592,
    "female":13.1739
  },
  {
    "both":24.9363,
    "male":30.9806,
    "female":23.5979
  },
  {
    "both":39.9618,
    "male":46.4143,
    "female":39.0208
  }
]